ruts/VERSION
ruts/__init__.py
ruts/basic_stats.py
ruts/components.py
ruts/constants.py
ruts/diversity_stats.py
ruts/extractors.py
ruts/morph_stats.py
ruts/readability_stats.py
ruts/utils.py
ruts/datasets/__init__.py
ruts/datasets/dataset.py
ruts/datasets/sov_chrest_lit.py
ruts/datasets/stalin_works.py
ruts/visualizers/__init__.py
ruts/visualizers/fingerprinting.py
ruts/visualizers/word_tree.py
ruts/visualizers/zipf.py
ruts-0.7.0.dist-info/LICENSE.txt
ruts-0.7.0.dist-info/METADATA
ruts-0.7.0.dist-info/WHEEL
ruts-0.7.0.dist-info/top_level.txt
ruts-0.7.0.dist-info/RECORD
