Metadata-Version: 2.1
Name: ruts
Version: 0.7.0
Summary: Russian Texts Statistics
Home-page: https://github.com/SergeyShk/ruTS
Author: Шкарин Сергей, Смирнова Екатерина
Author-email: kouki.sergey@gmail.com, ekanerina@yandex.ru
Maintainer: Шкарин Сергей
Maintainer-email: kouki.sergey@gmail.com
License: MIT License
Download-URL: https://github.com/SergeyShk/ruTS/archive/0.7.0.tar.gz
Project-URL: Source Code, https://github.com/SergeyShk/ruTS
Project-URL: Issue Tracker, https://github.com/SergeyShk/ruTS/issues
Project-URL: spaCy uniVerse, https://spacy.io/universe/project/ruts
Keywords: NLP,natural language processing,CL,computational linguistics,text analytics,russian
Platform: UNKNOWN
Classifier: Development Status :: 4 - Beta
Classifier: Operating System :: OS Independent
Classifier: License :: OSI Approved :: MIT License
Classifier: Programming Language :: Python :: 3.7
Classifier: Programming Language :: Python :: 3.8
Classifier: Programming Language :: Python :: 3.9
Classifier: Intended Audience :: Developers
Classifier: Intended Audience :: Education
Classifier: Intended Audience :: Information Technology
Classifier: Intended Audience :: Science/Research
Classifier: Topic :: Text Processing
Classifier: Topic :: Text Processing :: Linguistic
Classifier: Natural Language :: Russian
Requires-Python: >=3.7
Requires-Dist: scipy (>=1.6.0)
Requires-Dist: nltk
Requires-Dist: pymorphy2
Requires-Dist: razdel
Requires-Dist: spacy (>=3.0.0)
Requires-Dist: matplotlib (>=3.3.0)
Requires-Dist: numpy (>=1.20.0)
Requires-Dist: pandas
Requires-Dist: graphviz
